pyfanity/__init__.py
pyfanity/falseprofanities.py
pyfanity/profanities.py
pyfanity/pyfanity.py
pyfanity/replacements.py
pyfanity/test.py
pyfanity/testing.py
pyfanity-0.1.3.dist-info/LICENSE
pyfanity-0.1.3.dist-info/METADATA
pyfanity-0.1.3.dist-info/WHEEL
pyfanity-0.1.3.dist-info/RECORD
